README.md
setup.py
openstg/SqliteCounter.py
openstg/__init__.py
openstg/app.py
openstg/config.py
openstg/erpapi.py
openstg/stgapp.py
openstg/utils.py
openstg/ws_stg.py
openstg.egg-info/PKG-INFO
openstg.egg-info/SOURCES.txt
openstg.egg-info/dependency_links.txt
openstg.egg-info/requires.txt
openstg.egg-info/top_level.txt
openstg/api/__init__.py
openstg/api/constants.py
openstg/api/rtu.py
openstg/services/__init__.py
openstg/stg/__init__.py