Metadata-Version: 1.0
Name: openstg
Version: 1.19.0
Summary: API for STG-Protocol-DC Interface Specification
Home-page: https://github.com/gisce/openstg
Author: GISCE-TI, S.L.
Author-email: devel@gisce.net
License: GNU Affero General Public License v3
Platform: UNKNOWN
